esp_idf_kconfig/__init__.py
esp_idf_kconfig/__main__.py
esp_idf_kconfig/gen_kconfig_doc.py
kconfcheck/__init__.py
kconfcheck/__main__.py
kconfcheck/core.py
kconfgen/__init__.py
kconfgen/__main__.py
kconfgen/core.py
kconfserver/__init__.py
kconfserver/__main__.py
kconfserver/core.py
test/gen_kconfig_doc/test_kconfig_out.py
test/gen_kconfig_doc/test_target_visibility.py
test/kconfcheck/test_kconfcheck.py
test/kconfgen/test_kconfgen.py
test/kconfserver/test_kconfserver.py
test_pkg_kconfig-2.1.0.dist-info/LICENSE
test_pkg_kconfig-2.1.0.dist-info/METADATA
test_pkg_kconfig-2.1.0.dist-info/WHEEL
test_pkg_kconfig-2.1.0.dist-info/top_level.txt
test_pkg_kconfig-2.1.0.dist-info/RECORD
