Metadata-Version: 2.1
Name: test-pkg-kconfig
Version: 2.1.0
Summary: Kconfig tooling for esp-idf
Home-page: https://github.com/espressif/esp-idf-kconfig
Author: Espressif Systems
Author-email: 
License: 
Project-URL: Homepage, https://github.com/espressif/esp-idf-kconfig
Keywords: espressif,embedded,project,configuration,kconfig
Classifier: Development Status :: 5 - Production/Stable
Classifier: Intended Audience :: Developers
Classifier: Natural Language :: English
Classifier: Environment :: Console
Classifier: Topic :: Software Development :: Embedded Systems
Classifier: License :: OSI Approved :: Apache Software License
Classifier: Programming Language :: Python :: 3.7
Classifier: Programming Language :: Python :: 3.8
Classifier: Programming Language :: Python :: 3.9
Classifier: Programming Language :: Python :: 3.10
Classifier: Programming Language :: Python :: 3.11
Classifier: Operating System :: POSIX
Classifier: Operating System :: Microsoft :: Windows
Classifier: Operating System :: MacOS :: MacOS X
Requires-Python: >=3.7
License-File: LICENSE
Requires-Dist: kconfiglib >=13.7.1
Requires-Dist: windows-curses ; platform_system == "Windows"
Provides-Extra: dev
Requires-Dist: pre-commit ; extra == 'dev'
Requires-Dist: pexpect ; extra == 'dev'
Requires-Dist: commitizen ; extra == 'dev'
